mndynamics/__init__.py
mndynamics/plotting.py
mndynamics/utility.py
mndynamics/models/__init__.py
mndynamics/models/py/Erisir_Base.py
mndynamics/models/py/FN_Base.py
mndynamics/models/py/HH_Base.py
mndynamics/models/py/LIF_Base.py
mndynamics/models/py/QIF_Base.py
mndynamics/models/py/RTM_Base.py
mndynamics/models/py/Theta_Base.py
mndynamics/models/py/WB_Base.py
mndynamics/models/py/__init__.py
mndynamics/models/py/ch03.py
mndynamics/models/py/ch04.py
mndynamics/models/py/ch05.py
mndynamics/tests/__init__.py
mndynamics/tests/all_tests.py
mndynamics/tests/test_HH.py
mndynamics-0.1.0.dist-info/LICENSE.md
mndynamics-0.1.0.dist-info/METADATA
mndynamics-0.1.0.dist-info/WHEEL
mndynamics-0.1.0.dist-info/top_level.txt
mndynamics-0.1.0.dist-info/RECORD
