Metadata-Version: 2.1
Name: mndynamics
Version: 0.1.0
Summary: Modeling neural dynamcs
Home-page: https://github.com/Ziaeemehr/mndynamics
Author: Abolfazl Ziaeemehr
Author-email: a.ziaeemehr@gmail.com
License: UNKNOWN
Platform: UNKNOWN
Classifier: Programming Language :: Python :: 3
Classifier: License :: OSI Approved :: MIT License
Classifier: Operating System :: OS Independent
Requires-Python: >=3.1
Requires-Dist: matplotlib
Requires-Dist: networkx
Requires-Dist: numpy
Requires-Dist: scipy
Requires-Dist: tqdm
Requires-Dist: wheel
